{"moduleDefinition":{"range":[1,1,1,30],"value":{"type":"normal","normal":{"moduleName":{"range":[1,8,1,17],"value":["AnimState"]},"exposingList":{"range":[1,18,1,30],"value":{"type":"all","all":[1,27,1,29]}}}}},"imports":[{"range":[2,1,2,27],"value":{"moduleName":{"range":[2,8,2,13],"value":["Model"]},"moduleAlias":null,"exposingList":{"range":[2,14,2,27],"value":{"type":"all","all":[2,24,2,26]}}}},{"range":[3,1,3,29],"value":{"moduleName":{"range":[3,8,3,15],"value":["Message"]},"moduleAlias":null,"exposingList":{"range":[3,16,3,29],"value":{"type":"all","all":[3,26,3,28]}}}}],"declarations":[{"range":[6,1,7,42],"value":{"type":"function","function":{"documentation":null,"signature":null,"declaration":{"range":[6,1,7,42],"value":{"name":{"range":[6,1,6,7],"value":"crouch"},"arguments":[{"range":[6,8,6,14],"value":{"type":"var","var":{"value":"player"}}}],"expression":{"range":[7,5,7,42],"value":{"type":"recordUpdate","recordUpdate":{"name":{"range":[7,7,7,13],"value":"player"},"updates":[{"range":[7,15,7,28],"value":{"field":{"range":[7,15,7,19],"value":"anim"},"expression":{"range":[7,22,7,28],"value":{"type":"functionOrValue","functionOrValue":{"moduleName":[],"name":"Crouch"}}}}},{"range":[7,30,7,41],"value":{"field":{"range":[7,30,7,35],"value":"frame"},"expression":{"range":[7,38,7,39],"value":{"type":"integer","integer":0}}}}]}}}}}}}},{"range":[9,1,10,60],"value":{"type":"function","function":{"documentation":null,"signature":null,"declaration":{"range":[9,1,10,60],"value":{"name":{"range":[9,1,9,5],"value":"fall"},"arguments":[{"range":[9,6,9,12],"value":{"type":"var","var":{"value":"player"}}}],"expression":{"range":[10,5,10,60],"value":{"type":"recordUpdate","recordUpdate":{"name":{"range":[10,7,10,13],"value":"player"},"updates":[{"range":[10,15,10,27],"value":{"field":{"range":[10,15,10,19],"value":"anim"},"expression":{"range":[10,22,10,27],"value":{"type":"functionOrValue","functionOrValue":{"moduleName":[],"name":"Stand"}}}}},{"range":[10,29,10,38],"value":{"field":{"range":[10,29,10,34],"value":"frame"},"expression":{"range":[10,37,10,38],"value":{"type":"integer","integer":0}}}},{"range":[10,40,10,59],"value":{"field":{"range":[10,40,10,45],"value":"speed"},"expression":{"range":[10,48,10,58],"value":{"type":"application","application":[{"range":[10,48,10,54],"value":{"type":"functionOrValue","functionOrValue":{"moduleName":[],"name":"Vector"}}},{"range":[10,55,10,56],"value":{"type":"integer","integer":0}},{"range":[10,57,10,58],"value":{"type":"integer","integer":0}}]}}}}]}}}}}}}},{"range":[12,1,14,81],"value":{"type":"function","function":{"documentation":null,"signature":null,"declaration":{"range":[12,1,14,81],"value":{"name":{"range":[12,1,12,9],"value":"attacked"},"arguments":[{"range":[12,10,12,15],"value":{"type":"var","var":{"value":"speed"}}},{"range":[12,16,12,22],"value":{"type":"var","var":{"value":"player"}}}],"expression":{"range":[14,5,14,81],"value":{"type":"recordUpdate","recordUpdate":{"name":{"range":[14,7,14,13],"value":"player"},"updates":[{"range":[14,15,14,30],"value":{"field":{"range":[14,15,14,19],"value":"anim"},"expression":{"range":[14,22,14,30],"value":{"type":"functionOrValue","functionOrValue":{"moduleName":[],"name":"Attacked"}}}}},{"range":[14,32,14,41],"value":{"field":{"range":[14,32,14,37],"value":"frame"},"expression":{"range":[14,40,14,41],"value":{"type":"integer","integer":0}}}},{"range":[14,43,14,80],"value":{"field":{"range":[14,43,14,48],"value":"speed"},"expression":{"range":[14,51,14,80],"value":{"type":"application","application":[{"range":[14,51,14,57],"value":{"type":"functionOrValue","functionOrValue":{"moduleName":[],"name":"Vector"}}},{"range":[14,58,14,71],"value":{"type":"parenthesized","parenthesized":{"range":[14,64,14,70],"value":{"type":"application","application":[{"range":[14,64,14,66],"value":{"type":"recordAccess","recordAccess":{"expression":{"range":[14,59,14,64],"value":{"type":"functionOrValue","functionOrValue":{"moduleName":[],"name":"speed"}}},"name":{"range":[14,65,14,66],"value":"x"}}}},{"range":[14,67,14,68],"value":{"type":"operator","operator":"*"}},{"range":[14,69,14,70],"value":{"type":"integer","integer":2}}]}}}},{"range":[14,78,14,80],"value":{"type":"recordAccess","recordAccess":{"expression":{"range":[14,73,14,78],"value":{"type":"functionOrValue","functionOrValue":{"moduleName":[],"name":"speed"}}},"name":{"range":[14,79,14,80],"value":"y"}}}}]}}}}]}}}}}}}},{"range":[16,1,21,35],"value":{"type":"function","function":{"documentation":null,"signature":null,"declaration":{"range":[16,1,21,35],"value":{"name":{"range":[16,1,16,14],"value":"jumpdirection"},"arguments":[{"range":[16,15,16,28],"value":{"type":"var","var":{"value":"moveDirection"}}},{"range":[16,29,16,35],"value":{"type":"var","var":{"value":"player"}}}],"expression":{"range":[17,5,21,35],"value":{"type":"case","case":{"cases":[{"pattern":{"range":[18,9,18,13],"value":{"type":"named","named":{"qualified":{"moduleName":[],"name":"Left"},"patterns":[]}}},"expression":{"range":[19,13,19,35],"value":{"type":"recordUpdate","recordUpdate":{"name":{"range":[19,15,19,21],"value":"player"},"updates":[{"range":[19,23,19,34],"value":{"field":{"range":[19,23,19,30],"value":"jumpdir"},"expression":{"range":[19,33,19,34],"value":{"type":"functionOrValue","functionOrValue":{"moduleName":[],"name":"L"}}}}}]}}}},{"pattern":{"range":[20,9,20,14],"value":{"type":"named","named":{"qualified":{"moduleName":[],"name":"Right"},"patterns":[]}}},"expression":{"range":[21,13,21,35],"value":{"type":"recordUpdate","recordUpdate":{"name":{"range":[21,15,21,21],"value":"player"},"updates":[{"range":[21,23,21,34],"value":{"field":{"range":[21,23,21,30],"value":"jumpdir"},"expression":{"range":[21,33,21,34],"value":{"type":"functionOrValue","functionOrValue":{"moduleName":[],"name":"R"}}}}}]}}}}],"expression":{"range":[17,10,17,23],"value":{"type":"functionOrValue","functionOrValue":{"moduleName":[],"name":"moveDirection"}}}}}}}}}}},{"range":[23,1,24,74],"value":{"type":"function","function":{"documentation":null,"signature":null,"declaration":{"range":[23,1,24,74],"value":{"name":{"range":[23,1,23,6],"value":"stand"},"arguments":[{"range":[23,7,23,13],"value":{"type":"var","var":{"value":"player"}}}],"expression":{"range":[24,5,24,74],"value":{"type":"recordUpdate","recordUpdate":{"name":{"range":[24,7,24,13],"value":"player"},"updates":[{"range":[24,15,24,27],"value":{"field":{"range":[24,15,24,19],"value":"anim"},"expression":{"range":[24,22,24,27],"value":{"type":"functionOrValue","functionOrValue":{"moduleName":[],"name":"Stand"}}}}},{"range":[24,29,24,38],"value":{"field":{"range":[24,29,24,34],"value":"frame"},"expression":{"range":[24,37,24,38],"value":{"type":"integer","integer":0}}}},{"range":[24,40,24,58],"value":{"field":{"range":[24,40,24,45],"value":"speed"},"expression":{"range":[24,48,24,58],"value":{"type":"application","application":[{"range":[24,48,24,54],"value":{"type":"functionOrValue","functionOrValue":{"moduleName":[],"name":"Vector"}}},{"range":[24,55,24,56],"value":{"type":"integer","integer":0}},{"range":[24,57,24,58],"value":{"type":"integer","integer":0}}]}}}},{"range":[24,60,24,73],"value":{"field":{"range":[24,60,24,67],"value":"jumpdir"},"expression":{"range":[24,70,24,72],"value":{"type":"functionOrValue","functionOrValue":{"moduleName":[],"name":"Up"}}}}}]}}}}}}}},{"range":[26,1,33,92],"value":{"type":"function","function":{"documentation":null,"signature":null,"declaration":{"range":[26,1,33,92],"value":{"name":{"range":[26,1,26,5],"value":"jump"},"arguments":[{"range":[26,6,26,12],"value":{"type":"var","var":{"value":"player"}}}],"expression":{"range":[27,5,33,92],"value":{"type":"case","case":{"cases":[{"pattern":{"range":[28,9,28,10],"value":{"type":"named","named":{"qualified":{"moduleName":[],"name":"L"},"patterns":[]}}},"expression":{"range":[29,13,29,117],"value":{"type":"recordUpdate","recordUpdate":{"name":{"range":[29,15,29,21],"value":"player"},"updates":[{"range":[29,23,29,34],"value":{"field":{"range":[29,23,29,27],"value":"anim"},"expression":{"range":[29,30,29,34],"value":{"type":"functionOrValue","functionOrValue":{"moduleName":[],"name":"Jump"}}}}},{"range":[29,36,29,45],"value":{"field":{"range":[29,36,29,41],"value":"frame"},"expression":{"range":[29,44,29,45],"value":{"type":"integer","integer":0}}}},{"range":[29,47,29,116],"value":{"field":{"range":[29,47,29,52],"value":"speed"},"expression":{"range":[29,55,29,115],"value":{"type":"application","application":[{"range":[29,55,29,61],"value":{"type":"functionOrValue","functionOrValue":{"moduleName":[],"name":"Vector"}}},{"range":[29,62,29,88],"value":{"type":"parenthesized","parenthesized":{"range":[29,63,29,87],"value":{"type":"application","application":[{"range":[29,63,29,69],"value":{"type":"negation","negation":{"range":[29,64,29,69],"value":{"type":"float","float":0.001}}}},{"range":[29,69,29,70],"value":{"type":"operator","operator":"*"}},{"range":[29,76,29,87],"value":{"type":"recordAccess","recordAccess":{"expression":{"range":[29,70,29,76],"value":{"type":"functionOrValue","functionOrValue":{"moduleName":[],"name":"player"}}},"name":{"range":[29,77,29,87],"value":"chargetime"}}}}]}}}},{"range":[29,89,29,115],"value":{"type":"parenthesized","parenthesized":{"range":[29,90,29,114],"value":{"type":"application","application":[{"range":[29,90,29,96],"value":{"type":"negation","negation":{"range":[29,91,29,96],"value":{"type":"float","float":0.001}}}},{"range":[29,96,29,97],"value":{"type":"operator","operator":"*"}},{"range":[29,103,29,114],"value":{"type":"recordAccess","recordAccess":{"expression":{"range":[29,97,29,103],"value":{"type":"functionOrValue","functionOrValue":{"moduleName":[],"name":"player"}}},"name":{"range":[29,104,29,114],"value":"chargetime"}}}}]}}}}]}}}}]}}}},{"pattern":{"range":[30,9,30,10],"value":{"type":"named","named":{"qualified":{"moduleName":[],"name":"R"},"patterns":[]}}},"expression":{"range":[31,13,31,116],"value":{"type":"recordUpdate","recordUpdate":{"name":{"range":[31,15,31,21],"value":"player"},"updates":[{"range":[31,23,31,34],"value":{"field":{"range":[31,23,31,27],"value":"anim"},"expression":{"range":[31,30,31,34],"value":{"type":"functionOrValue","functionOrValue":{"moduleName":[],"name":"Jump"}}}}},{"range":[31,36,31,45],"value":{"field":{"range":[31,36,31,41],"value":"frame"},"expression":{"range":[31,44,31,45],"value":{"type":"integer","integer":0}}}},{"range":[31,47,31,115],"value":{"field":{"range":[31,47,31,52],"value":"speed"},"expression":{"range":[31,55,31,114],"value":{"type":"application","application":[{"range":[31,55,31,61],"value":{"type":"functionOrValue","functionOrValue":{"moduleName":[],"name":"Vector"}}},{"range":[31,62,31,87],"value":{"type":"parenthesized","parenthesized":{"range":[31,63,31,86],"value":{"type":"application","application":[{"range":[31,63,31,68],"value":{"type":"float","float":0.001}},{"range":[31,68,31,69],"value":{"type":"operator","operator":"*"}},{"range":[31,75,31,86],"value":{"type":"recordAccess","recordAccess":{"expression":{"range":[31,69,31,75],"value":{"type":"functionOrValue","functionOrValue":{"moduleName":[],"name":"player"}}},"name":{"range":[31,76,31,86],"value":"chargetime"}}}}]}}}},{"range":[31,88,31,114],"value":{"type":"parenthesized","parenthesized":{"range":[31,89,31,113],"value":{"type":"application","application":[{"range":[31,89,31,95],"value":{"type":"negation","negation":{"range":[31,90,31,95],"value":{"type":"float","float":0.001}}}},{"range":[31,95,31,96],"value":{"type":"operator","operator":"*"}},{"range":[31,102,31,113],"value":{"type":"recordAccess","recordAccess":{"expression":{"range":[31,96,31,102],"value":{"type":"functionOrValue","functionOrValue":{"moduleName":[],"name":"player"}}},"name":{"range":[31,103,31,113],"value":"chargetime"}}}}]}}}}]}}}}]}}}},{"pattern":{"range":[32,9,32,11],"value":{"type":"named","named":{"qualified":{"moduleName":[],"name":"Up"},"patterns":[]}}},"expression":{"range":[33,13,33,92],"value":{"type":"recordUpdate","recordUpdate":{"name":{"range":[33,15,33,21],"value":"player"},"updates":[{"range":[33,23,33,34],"value":{"field":{"range":[33,23,33,27],"value":"anim"},"expression":{"range":[33,30,33,34],"value":{"type":"functionOrValue","functionOrValue":{"moduleName":[],"name":"Jump"}}}}},{"range":[33,36,33,45],"value":{"field":{"range":[33,36,33,41],"value":"frame"},"expression":{"range":[33,44,33,45],"value":{"type":"integer","integer":0}}}},{"range":[33,47,33,91],"value":{"field":{"range":[33,47,33,52],"value":"speed"},"expression":{"range":[33,55,33,90],"value":{"type":"application","application":[{"range":[33,55,33,61],"value":{"type":"functionOrValue","functionOrValue":{"moduleName":[],"name":"Vector"}}},{"range":[33,62,33,63],"value":{"type":"integer","integer":0}},{"range":[33,64,33,90],"value":{"type":"parenthesized","parenthesized":{"range":[33,65,33,89],"value":{"type":"application","application":[{"range":[33,65,33,71],"value":{"type":"negation","negation":{"range":[33,66,33,71],"value":{"type":"float","float":0.001}}}},{"range":[33,71,33,72],"value":{"type":"operator","operator":"*"}},{"range":[33,78,33,89],"value":{"type":"recordAccess","recordAccess":{"expression":{"range":[33,72,33,78],"value":{"type":"functionOrValue","functionOrValue":{"moduleName":[],"name":"player"}}},"name":{"range":[33,79,33,89],"value":"chargetime"}}}}]}}}}]}}}}]}}}}],"expression":{"range":[27,16,27,24],"value":{"type":"recordAccess","recordAccess":{"expression":{"range":[27,10,27,16],"value":{"type":"functionOrValue","functionOrValue":{"moduleName":[],"name":"player"}}},"name":{"range":[27,17,27,24],"value":"jumpdir"}}}}}}}}}}}},{"range":[35,1,45,1],"value":{"type":"function","function":{"documentation":null,"signature":null,"declaration":{"range":[35,1,45,1],"value":{"name":{"range":[35,1,35,5],"value":"walk"},"arguments":[{"range":[35,6,35,19],"value":{"type":"var","var":{"value":"moveDirection"}}},{"range":[35,20,35,26],"value":{"type":"var","var":{"value":"player"}}}],"expression":{"range":[36,5,45,1],"value":{"type":"ifBlock","ifBlock":{"clause":{"range":[36,14,36,28],"value":{"type":"application","application":[{"range":[36,14,36,19],"value":{"type":"recordAccess","recordAccess":{"expression":{"range":[36,8,36,14],"value":{"type":"functionOrValue","functionOrValue":{"moduleName":[],"name":"player"}}},"name":{"range":[36,15,36,19],"value":"anim"}}}},{"range":[36,20,36,22],"value":{"type":"operator","operator":"=="}},{"range":[36,23,36,28],"value":{"type":"functionOrValue","functionOrValue":{"moduleName":[],"name":"Stand"}}}]}},"then":{"range":[37,9,41,102],"value":{"type":"case","case":{"cases":[{"pattern":{"range":[38,13,38,17],"value":{"type":"named","named":{"qualified":{"moduleName":[],"name":"Left"},"patterns":[]}}},"expression":{"range":[39,17,39,103],"value":{"type":"recordUpdate","recordUpdate":{"name":{"range":[39,19,39,25],"value":"player"},"updates":[{"range":[39,27,39,38],"value":{"field":{"range":[39,27,39,31],"value":"anim"},"expression":{"range":[39,34,39,38],"value":{"type":"functionOrValue","functionOrValue":{"moduleName":[],"name":"Walk"}}}}},{"range":[39,41,39,65],"value":{"field":{"range":[39,41,39,50],"value":"direction"},"expression":{"range":[39,52,39,65],"value":{"type":"functionOrValue","functionOrValue":{"moduleName":[],"name":"moveDirection"}}}}},{"range":[39,67,39,88],"value":{"field":{"range":[39,67,39,72],"value":"speed"},"expression":{"range":[39,75,39,88],"value":{"type":"application","application":[{"range":[39,75,39,81],"value":{"type":"functionOrValue","functionOrValue":{"moduleName":[],"name":"Vector"}}},{"range":[39,82,39,86],"value":{"type":"negation","negation":{"range":[39,83,39,86],"value":{"type":"float","float":0.2}}}},{"range":[39,87,39,88],"value":{"type":"integer","integer":0}}]}}}},{"range":[39,90,39,102],"value":{"field":{"range":[39,90,39,97],"value":"jumpdir"},"expression":{"range":[39,100,39,101],"value":{"type":"functionOrValue","functionOrValue":{"moduleName":[],"name":"L"}}}}}]}}}},{"pattern":{"range":[40,13,40,18],"value":{"type":"named","named":{"qualified":{"moduleName":[],"name":"Right"},"patterns":[]}}},"expression":{"range":[41,17,41,102],"value":{"type":"recordUpdate","recordUpdate":{"name":{"range":[41,19,41,25],"value":"player"},"updates":[{"range":[41,27,41,38],"value":{"field":{"range":[41,27,41,31],"value":"anim"},"expression":{"range":[41,34,41,38],"value":{"type":"functionOrValue","functionOrValue":{"moduleName":[],"name":"Walk"}}}}},{"range":[41,41,41,65],"value":{"field":{"range":[41,41,41,50],"value":"direction"},"expression":{"range":[41,52,41,65],"value":{"type":"functionOrValue","functionOrValue":{"moduleName":[],"name":"moveDirection"}}}}},{"range":[41,67,41,87],"value":{"field":{"range":[41,67,41,72],"value":"speed"},"expression":{"range":[41,75,41,87],"value":{"type":"application","application":[{"range":[41,75,41,81],"value":{"type":"functionOrValue","functionOrValue":{"moduleName":[],"name":"Vector"}}},{"range":[41,82,41,85],"value":{"type":"float","float":0.2}},{"range":[41,86,41,87],"value":{"type":"integer","integer":0}}]}}}},{"range":[41,89,41,101],"value":{"field":{"range":[41,89,41,96],"value":"jumpdir"},"expression":{"range":[41,99,41,100],"value":{"type":"functionOrValue","functionOrValue":{"moduleName":[],"name":"R"}}}}}]}}}}],"expression":{"range":[37,14,37,27],"value":{"type":"functionOrValue","functionOrValue":{"moduleName":[],"name":"moveDirection"}}}}}},"else":{"range":[43,10,43,16],"value":{"type":"functionOrValue","functionOrValue":{"moduleName":[],"name":"player"}}}}}}}}}}},{"range":[45,1,49,1],"value":{"type":"function","function":{"documentation":null,"signature":null,"declaration":{"range":[45,1,49,1],"value":{"name":{"range":[45,1,45,7],"value":"attack"},"arguments":[{"range":[45,8,45,14],"value":{"type":"var","var":{"value":"player"}}}],"expression":{"range":[46,5,49,1],"value":{"type":"ifBlock","ifBlock":{"clause":{"range":[46,14,46,28],"value":{"type":"application","application":[{"range":[46,14,46,19],"value":{"type":"recordAccess","recordAccess":{"expression":{"range":[46,8,46,14],"value":{"type":"functionOrValue","functionOrValue":{"moduleName":[],"name":"player"}}},"name":{"range":[46,15,46,19],"value":"anim"}}}},{"range":[46,20,46,22],"value":{"type":"operator","operator":"=="}},{"range":[46,23,46,28],"value":{"type":"functionOrValue","functionOrValue":{"moduleName":[],"name":"Stand"}}}]}},"then":{"range":[47,9,47,65],"value":{"type":"recordUpdate","recordUpdate":{"name":{"range":[47,11,47,17],"value":"player"},"updates":[{"range":[47,19,47,32],"value":{"field":{"range":[47,19,47,23],"value":"anim"},"expression":{"range":[47,26,47,32],"value":{"type":"functionOrValue","functionOrValue":{"moduleName":[],"name":"Attack"}}}}},{"range":[47,34,47,43],"value":{"field":{"range":[47,34,47,39],"value":"frame"},"expression":{"range":[47,42,47,43],"value":{"type":"integer","integer":0}}}},{"range":[47,45,47,64],"value":{"field":{"range":[47,45,47,50],"value":"speed"},"expression":{"range":[47,53,47,63],"value":{"type":"application","application":[{"range":[47,53,47,59],"value":{"type":"functionOrValue","functionOrValue":{"moduleName":[],"name":"Vector"}}},{"range":[47,60,47,61],"value":{"type":"integer","integer":0}},{"range":[47,62,47,63],"value":{"type":"integer","integer":0}}]}}}}]}}},"else":{"range":[48,10,48,16],"value":{"type":"functionOrValue","functionOrValue":{"moduleName":[],"name":"player"}}}}}}}}}}},{"range":[49,1,50,29],"value":{"type":"function","function":{"documentation":null,"signature":null,"declaration":{"range":[49,1,50,29],"value":{"name":{"range":[49,1,49,7],"value":"charge"},"arguments":[{"range":[49,8,49,14],"value":{"type":"var","var":{"value":"player"}}}],"expression":{"range":[50,5,50,29],"value":{"type":"recordUpdate","recordUpdate":{"name":{"range":[50,6,50,12],"value":"player"},"updates":[{"range":[50,15,50,28],"value":{"field":{"range":[50,15,50,19],"value":"anim"},"expression":{"range":[50,22,50,28],"value":{"type":"functionOrValue","functionOrValue":{"moduleName":[],"name":"Charge"}}}}}]}}}}}}}}],"comments":[]}